vicon_nexus_unity_stream_py/__init__.py
vicon_nexus_unity_stream_py/_main.py
vicon_nexus_unity_stream_py/_utils.py
vicon_nexus_unity_stream_py/cli.py
vicon_nexus_unity_stream_py/static/index.html
vicon_nexus_unity_stream_py/tests/__init__.py
vicon_nexus_unity_stream_py/tests/conftest.py
vicon_nexus_unity_stream_py/tests/test_utils.py
vicon_nexus_unity_stream_py-0.3.dist-info/entry_points.txt
vicon_nexus_unity_stream_py-0.3.dist-info/LICENSE.md
vicon_nexus_unity_stream_py-0.3.dist-info/METADATA
vicon_nexus_unity_stream_py-0.3.dist-info/WHEEL
vicon_nexus_unity_stream_py-0.3.dist-info/RECORD
