Metadata-Version: 2.1
Name: vicon_nexus_unity_stream_py
Version: 0.3
Summary: Python script to stream data from vicon nexus to unity
Home-page: https://pypi.org/project/vicon_nexus_unity_stream_py
License: MIT
Author: Ahmed Shariff
Author-email: shariff.mfa@outlook.com
Requires-Python: >=3.8,<4.0
Classifier: Development Status :: 1 - Planning
Classifier: License :: OSI Approved :: MIT License
Classifier: Natural Language :: English
Classifier: Operating System :: OS Independent
Classifier: Programming Language :: Python
Classifier: Programming Language :: Python :: 3
Classifier: Programming Language :: Python :: 3.8
Classifier: Programming Language :: Python :: 3.9
Classifier: Programming Language :: Python :: 3.10
Classifier: Programming Language :: Python :: 3.11
Classifier: Programming Language :: Python :: 3.12
Requires-Dist: click (>=8.1.3)
Requires-Dist: fastapi (>=0.99,<0.100)
Requires-Dist: importlib-metadata (>=8.0.0)
Requires-Dist: loguru (>=0.5.0)
Requires-Dist: pandas (>=1.5.1)
Project-URL: Documentation, https://vicon_nexus_unity_stream_py.readthedocs.io
Project-URL: Repository, https://github.com/ovi-lab/vicon-nexus-unity-stream-py
